bapsf_motion/__init__.py
bapsf_motion/actors/__init__.py
bapsf_motion/actors/axis_.py
bapsf_motion/actors/base.py
bapsf_motion/actors/drive_.py
bapsf_motion/actors/manager_.py
bapsf_motion/actors/motion_group_.py
bapsf_motion/actors/motor_.py
bapsf_motion/actors/demos/__init__.py
bapsf_motion/actors/demos/drive_timed_run_1D.py
bapsf_motion/actors/demos/drive_timed_run_2D.py
bapsf_motion/actors/demos/mgroup_timed_run_2D.py
bapsf_motion/actors/tests/__init__.py
bapsf_motion/examples/20240627_2D_test_setup.toml
bapsf_motion/examples/20241004_2D_test_setup.toml
bapsf_motion/examples/bapsf_motion.toml
bapsf_motion/examples/benchtop_motion_group.toml
bapsf_motion/examples/benchtop_run.toml
bapsf_motion/examples/mg_1d.toml
bapsf_motion/examples/mg_2d_strb_test_setup.toml
bapsf_motion/examples/motion_group.toml
bapsf_motion/gui/__init__.py
bapsf_motion/gui/helpers.py
bapsf_motion/gui/lapd_xy_transform_calculator.py
bapsf_motion/gui/motor.py
bapsf_motion/gui/_images/LaPDXYTransform_diagram.png
bapsf_motion/gui/configure/__init__.py
bapsf_motion/gui/configure/bases.py
bapsf_motion/gui/configure/configure.qss
bapsf_motion/gui/configure/configure_.py
bapsf_motion/gui/configure/drive_overlay.py
bapsf_motion/gui/configure/helpers.py
bapsf_motion/gui/configure/motion_builder_overlay.py
bapsf_motion/gui/configure/motion_group_widget.py
bapsf_motion/gui/configure/motion_space_display.py
bapsf_motion/gui/configure/parameter_hints.toml
bapsf_motion/gui/configure/transform_overlay.py
bapsf_motion/gui/widgets/__init__.py
bapsf_motion/gui/widgets/buttons.py
bapsf_motion/gui/widgets/logging.py
bapsf_motion/gui/widgets/misc.py
bapsf_motion/motion_builder/__init__.py
bapsf_motion/motion_builder/core.py
bapsf_motion/motion_builder/item.py
bapsf_motion/motion_builder/exclusions/__init__.py
bapsf_motion/motion_builder/exclusions/base.py
bapsf_motion/motion_builder/exclusions/circular.py
bapsf_motion/motion_builder/exclusions/divider.py
bapsf_motion/motion_builder/exclusions/helpers.py
bapsf_motion-2025.7.0.dist-info/METADATA
bapsf_motion-2025.7.0.dist-info/WHEEL
bapsf_motion-2025.7.0.dist-info/dependency_links.txt
bapsf_motion-2025.7.0.dist-info/top_level.txt
bapsf_motion-2025.7.0.dist-info/RECORD
