Metadata-Version: 2.4
Name: bapsf_motion
Version: 2025.7.0
Summary: Package for controlling motion devices in a BaPSF DAQ system
Author: Basic Plasma Science Facility
Keywords: plasma physics,plasma,science,bapsf,motion
Classifier: Development Status :: 1 - Planning
Classifier: Intended Audience :: Science/Research
Classifier: Operating System :: OS Independent
Classifier: Programming Language :: Python :: 3
Classifier: Programming Language :: Python :: 3.7
Classifier: Programming Language :: Python :: 3.8
Classifier: Programming Language :: Python :: 3.8
Classifier: Programming Language :: Python :: 3.9
Classifier: Programming Language :: Python :: 3.10
Classifier: Topic :: Scientific/Engineering :: Physics
Classifier: Topic :: Scientific/Engineering :: Astronomy
Provides: bapsf_motion
Requires-Python: >=3.7
Requires-Dist: astropy
Requires-Dist: importlib_metadata; python_version < "3.8"
Requires-Dist: numpy
Requires-Dist: numpydoc
Requires-Dist: tomli; python_version < "3.11"
Requires-Dist: tomli_w
Requires-Dist: tqdm
Requires-Dist: xarray
Provides-Extra: 32bit
Requires-Dist: kiwisolver<1.4.7; extra == "32bit"
Requires-Dist: numpy<2.0,>=1.18.1; extra == "32bit"
Requires-Dist: matplotlib<3.9.0,>=3.3.0; extra == "32bit"
Requires-Dist: pandas<=2.0.3; extra == "32bit"
Provides-Extra: gui
Requires-Dist: matplotlib; extra == "gui"
Requires-Dist: pygame; extra == "gui"
Requires-Dist: PySide6; python_version >= "3.10" and extra == "gui"
Requires-Dist: PySide6<=6.3.1; python_version < "3.10" and extra == "gui"
Requires-Dist: qtawesome; extra == "gui"
Provides-Extra: tests
Requires-Dist: matplotlib; extra == "tests"
Requires-Dist: pygame; extra == "tests"
Requires-Dist: PySide6; python_version >= "3.10" and extra == "tests"
Requires-Dist: PySide6<=6.3.1; python_version < "3.10" and extra == "tests"
Requires-Dist: qtawesome; extra == "tests"
Requires-Dist: pytest>=5.1; extra == "tests"
Provides-Extra: docs
Requires-Dist: matplotlib; extra == "docs"
Requires-Dist: pygame; extra == "docs"
Requires-Dist: PySide6; python_version >= "3.10" and extra == "docs"
Requires-Dist: PySide6<=6.3.1; python_version < "3.10" and extra == "docs"
Requires-Dist: qtawesome; extra == "docs"
Requires-Dist: docutils>=0.18.1; extra == "docs"
Requires-Dist: ipython; extra == "docs"
Requires-Dist: jinja2>=3.1.2; extra == "docs"
Requires-Dist: nbsphinx>=0.9.1; extra == "docs"
Requires-Dist: numpydoc>=1.5.0; extra == "docs"
Requires-Dist: pillow>=9.5.0; extra == "docs"
Requires-Dist: pygments>=2.15.0; extra == "docs"
Requires-Dist: sphinx<=7.3.7,>=6.1.3; extra == "docs"
Requires-Dist: sphinx-changelog>=1.3.0; extra == "docs"
Requires-Dist: sphinx-codeautolink>=0.15.0; extra == "docs"
Requires-Dist: sphinx-copybutton>=0.5.1; extra == "docs"
Requires-Dist: sphinx-gallery>=0.12.2; extra == "docs"
Requires-Dist: sphinx-hoverxref>=1.1.1; extra == "docs"
Requires-Dist: sphinx-issues>=3.0.1; extra == "docs"
Requires-Dist: sphinx-notfound-page>=0.8.3; extra == "docs"
Requires-Dist: sphinx-reredirects>=0.1.1; extra == "docs"
Requires-Dist: sphinx_rtd_theme>=1.2.0; extra == "docs"
Requires-Dist: sphinx_tabs<=3.4.5,>=3.4.1; extra == "docs"
Requires-Dist: sphinxcontrib-bibtex>=2.5.0; extra == "docs"
Requires-Dist: towncrier>=22.12; extra == "docs"
Requires-Dist: tox>=4.4.0; extra == "docs"
Requires-Dist: plasmapy_sphinx; extra == "docs"
Provides-Extra: extras
Requires-Dist: matplotlib; extra == "extras"
Requires-Dist: pygame; extra == "extras"
Requires-Dist: PySide6; python_version >= "3.10" and extra == "extras"
Requires-Dist: PySide6<=6.3.1; python_version < "3.10" and extra == "extras"
Requires-Dist: qtawesome; extra == "extras"
Requires-Dist: black; extra == "extras"
Requires-Dist: isort; extra == "extras"
Provides-Extra: developer
Requires-Dist: matplotlib; extra == "developer"
Requires-Dist: pygame; extra == "developer"
Requires-Dist: PySide6; python_version >= "3.10" and extra == "developer"
Requires-Dist: PySide6<=6.3.1; python_version < "3.10" and extra == "developer"
Requires-Dist: qtawesome; extra == "developer"
Requires-Dist: matplotlib; extra == "developer"
Requires-Dist: pygame; extra == "developer"
Requires-Dist: PySide6; python_version >= "3.10" and extra == "developer"
Requires-Dist: PySide6<=6.3.1; python_version < "3.10" and extra == "developer"
Requires-Dist: qtawesome; extra == "developer"
Requires-Dist: docutils>=0.18.1; extra == "developer"
Requires-Dist: ipython; extra == "developer"
Requires-Dist: jinja2>=3.1.2; extra == "developer"
Requires-Dist: nbsphinx>=0.9.1; extra == "developer"
Requires-Dist: numpydoc>=1.5.0; extra == "developer"
Requires-Dist: pillow>=9.5.0; extra == "developer"
Requires-Dist: pygments>=2.15.0; extra == "developer"
Requires-Dist: sphinx<=7.3.7,>=6.1.3; extra == "developer"
Requires-Dist: sphinx-changelog>=1.3.0; extra == "developer"
Requires-Dist: sphinx-codeautolink>=0.15.0; extra == "developer"
Requires-Dist: sphinx-copybutton>=0.5.1; extra == "developer"
Requires-Dist: sphinx-gallery>=0.12.2; extra == "developer"
Requires-Dist: sphinx-hoverxref>=1.1.1; extra == "developer"
Requires-Dist: sphinx-issues>=3.0.1; extra == "developer"
Requires-Dist: sphinx-notfound-page>=0.8.3; extra == "developer"
Requires-Dist: sphinx-reredirects>=0.1.1; extra == "developer"
Requires-Dist: sphinx_rtd_theme>=1.2.0; extra == "developer"
Requires-Dist: sphinx_tabs<=3.4.5,>=3.4.1; extra == "developer"
Requires-Dist: sphinxcontrib-bibtex>=2.5.0; extra == "developer"
Requires-Dist: towncrier>=22.12; extra == "developer"
Requires-Dist: tox>=4.4.0; extra == "developer"
Requires-Dist: plasmapy_sphinx; extra == "developer"
Requires-Dist: matplotlib; extra == "developer"
Requires-Dist: pygame; extra == "developer"
Requires-Dist: PySide6; python_version >= "3.10" and extra == "developer"
Requires-Dist: PySide6<=6.3.1; python_version < "3.10" and extra == "developer"
Requires-Dist: qtawesome; extra == "developer"
Requires-Dist: pytest>=5.1; extra == "developer"
Requires-Dist: matplotlib; extra == "developer"
Requires-Dist: pygame; extra == "developer"
Requires-Dist: PySide6; python_version >= "3.10" and extra == "developer"
Requires-Dist: PySide6<=6.3.1; python_version < "3.10" and extra == "developer"
Requires-Dist: qtawesome; extra == "developer"
Requires-Dist: black; extra == "developer"
Requires-Dist: isort; extra == "developer"
Dynamic: provides
